sksurgerygoicppython.cpython-37m-darwin.so
scikit_surgerygoicp-0.2.5.dist-info/LICENSE.txt
scikit_surgerygoicp-0.2.5.dist-info/METADATA
scikit_surgerygoicp-0.2.5.dist-info/WHEEL
scikit_surgerygoicp-0.2.5.dist-info/top_level.txt
scikit_surgerygoicp-0.2.5.dist-info/RECORD
